asr_decoder/__init__.py
asr_decoder/context_graph.py
asr_decoder/ctc_decoder.py
asr_decoder/prefix_score.py
asr_decoder/utils.py
asr_decoder-0.1.1.dist-info/licenses/LICENSE
asr_decoder-0.1.1.dist-info/METADATA
asr_decoder-0.1.1.dist-info/WHEEL
asr_decoder-0.1.1.dist-info/top_level.txt
asr_decoder-0.1.1.dist-info/RECORD
